llamphouse/core/__init__.py
llamphouse/core/_exceptions.py
llamphouse/core/assistant.py
llamphouse/core/context.py
llamphouse/core/llamphouse.py
llamphouse/core/_utils/__init__.py
llamphouse/core/_utils/_utils.py
llamphouse/core/api_interfaces/base_api_interface.py
llamphouse/core/auth/__init__.py
llamphouse/core/auth/base_auth.py
llamphouse/core/auth/key_auth.py
llamphouse/core/data_stores/__init__.py
llamphouse/core/data_stores/base_data_store.py
llamphouse/core/data_stores/in_memory_store.py
llamphouse/core/data_stores/postgres_store.py
llamphouse/core/data_stores/retention.py
llamphouse/core/database/__init__.py
llamphouse/core/database/models.py
llamphouse/core/middlewares/__init__.py
llamphouse/core/middlewares/auth_middleware.py
llamphouse/core/middlewares/catch_exceptions_middleware.py
llamphouse/core/queue/__init__.py
llamphouse/core/queue/base_queue.py
llamphouse/core/queue/exceptions.py
llamphouse/core/queue/in_memory_queue.py
llamphouse/core/queue/types.py
llamphouse/core/routes/__init__.py
llamphouse/core/routes/assistant.py
llamphouse/core/routes/message.py
llamphouse/core/routes/run.py
llamphouse/core/routes/run_step.py
llamphouse/core/routes/threads.py
llamphouse/core/streaming/__init__.py
llamphouse/core/streaming/base_event_handler.py
llamphouse/core/streaming/emitter.py
llamphouse/core/streaming/event.py
llamphouse/core/streaming/stream_events.py
llamphouse/core/streaming/adapters/__init__.py
llamphouse/core/streaming/adapters/anthropic.py
llamphouse/core/streaming/adapters/base_stream_adapter.py
llamphouse/core/streaming/adapters/gemini.py
llamphouse/core/streaming/adapters/openai_chat_completions.py
llamphouse/core/streaming/adapters/registry.py
llamphouse/core/streaming/event_queue/base_event_queue.py
llamphouse/core/streaming/event_queue/in_memory_event_queue.py
llamphouse/core/streaming/event_queue/janus_event_queue.py
llamphouse/core/types/__init__.py
llamphouse/core/types/assistant.py
llamphouse/core/types/completion.py
llamphouse-1.0.1.dist-info/licenses/LICENSE
llamphouse-1.0.1.dist-info/METADATA
llamphouse-1.0.1.dist-info/WHEEL
llamphouse-1.0.1.dist-info/top_level.txt
llamphouse-1.0.1.dist-info/RECORD
