Metadata-Version: 2.4
Name: llamphouse
Version: 1.0.1
Summary: LLAMPHouse OpenAI Assistant Server
Author-email: "llamp.ai" <pieter@llamp.ai>
Requires-Python: >=3.10
License-File: LICENSE
Requires-Dist: fastapi<0.130,>=0.100.0
Requires-Dist: uvicorn<0.41,>=0.15.0
Requires-Dist: SQLAlchemy<2.1.0,>=1.4.0
Requires-Dist: psycopg2-binary<3,>=2.9.9
Requires-Dist: alembic<2,>=1.17.2
Requires-Dist: python-dotenv<2,>=1.2.1
Requires-Dist: janus<3,>=2.0.0
Dynamic: license-file
